{
"recipes": [
    {
	"id": "recon.sobibor.lowtrauma",
	"actionid": "recon",
	"label": "搜索梦魇中的景象",
	"startdescription": "梦魇或许会扭曲人的回忆，但这个地方几乎与我记忆中一摸一样。当我行于这古老、结霜的道路时，我会发现些什么？",
	"description": "我找到了一些东西。",
	"requirements": {
	    "sobibor.here": 1
	},
	"extantreqs": {
	    "damage.mind": -3
	},
	"aspects": {
	    "fatiguing": 1
	},
	"warmup": 30,
	"craftable": true,
	"internaldeck": {
	    "spec": [
		"side.sobibor",
		"side.sobibor",
		"side.sobibor",
		"side.sobibor",
		"foe.prisoners",
		"foe.prisoners",
		"foe.prisoners",
		"foe.prisoners",
		"mem.regret",
		"mem.rage",
		"mem.fear",
		"mem.grief",
		"mem.calm",
		"mem.ingenuity",
		"mem.revelation",
		"foe.grame.inactive",
		"foe.shade.inactive",
		"foe.campguard",
		"foe.watchdog",
		"foe.searchlight",
		"foe.starvation",
		"foe.cold"
	    ],
	    "draws": 1,
	    "resetonexhaustion": true
	},
    },
    {
	"id": "recon.sobibor.hightrauma",
	"actionid": "recon",
	"label": "在疯狂的边缘搜索噩梦",
	"startdescription": "我正行于决心与融解的分界线上。我能听到狼渴望血的狂嚎。当我筛过这古老的痛苦，我将找到什么？又有什么将找上我？",
	"description": "我找到了一些东西。",
	"requirements": {
	    "sobibor.here": 1
	},
	"extantreqs": {
	    "damage.mind": 3
	},
	"aspects": {
	    "fatiguing": 1
	},
	"warmup": 30,
	"craftable": true,
	"internaldeck": {
	    "spec": [
		"side.sobibor",
		"side.sobibor",
		"agony",
		"hatred",
		"despair",
		"agony",
		"hatred",
		"despair",
		"mem.regret",
		"mem.rage",
		"mem.fear",
		"mem.grief",
		"mem.calm",
		"mem.ingenuity",
		"mem.revelation",
		"foe.prisoners",
		"foe.prisoners",
		"foe.grame",
		"foe.shade",
		"foe.grame",
		"foe.shade",
		"foe.grame",
		"foe.shade",
		"contemplation.sobibor",
		"contemplation.sobibor"
	    ],
	    "draws": 1,
	    "resetonexhaustion": true
	},
    },
    {
	"id": "recon.cityinflames.scouts",
	"actionid": "recon",
	"label": "在混乱与痛苦中搜索",
	"startdescription": "筛过灰烬，捡拾尸体。深吸一口气，便能闻到燃烧的明日。",
	"description": "我们找到了一些东西。",
	"requirements": {
	    "friend": 1,
	    "shrine.wolf": 1
	},
	"aspects": {
	    "fatiguing": 1
	},
	"warmup": 15,
	"craftable": true,
	"internaldeck": {
	    "spec": [
		"op.fire",
		"op.fire",
		"op.ruins",
		"op.ruins",
		"foe.wrake",
		"foe.splinter",
		"op.wolfdivided",
	    ],
	    "draws": 1,
	    "resetonexhaustion": true
	},
	"alt": [
	    {
		"id": "uncover.enemy",
		"additional": true,
		"chance": 40
	    }
	],
	"linked": [
	    {
		"id": "findkazimirsword",
		"chance": 40
	    },
	    {
		"id": "find.sergei.comeforsword",
		"chance": 30
	    }
	]
    },
    {
	"id": "recon.cityinflames",
	"actionid": "recon",
	"label": "在混乱与痛苦中搜索",
	"startdescription": "筛过灰烬，捡拾尸体。深吸一口气，便能闻到燃烧的明日。",
	"description": "我们找到了一些东西。",
	"requirements": {
	    "friend": -1,
	    "shrine.wolf": 1
	},
	"aspects": {
	    "fatiguing": 1
	},
	"warmup": 30,
	"craftable": true,
	"internaldeck": {
	    "spec": [
		"op.fire",
		"op.fire",
		"op.ruins",
		"op.ruins",
		"foe.wrake",
		"foe.splinter",
		"op.wolfdivided",
	    ],
	    "draws": 1,
	    "resetonexhaustion": true
	},
	"alt": [
	    {
		"id": "uncover.enemy",
		"additional": true,
		"chance": 40
	    }
	],
	"linked": [
	    {
		"id": "findkazimirsword",
		"chance": 40
	    },
	    {
		"id": "find.sergei.comeforsword",
		"chance": 30
	    }
	]
    },
    {
	"id": "recon.wasteland.a.contemnant.scouts",
	"actionid": "recon",
	"label": "搜索战火摧残的地区？",
	"startdescription": "走入夜晚那灰暗的死寂，你就能找到什么。也有什么将找上你。",
	"description": "找到了。",
	"requirements": {
	    "friend": 1,
	    "wasteland.a.contemnant": 1
	},
	"aspects": {
	    "fatiguing": 1
	},
	"warmup": 15,
	"craftable": true,
	"internaldeck": {
	    "spec": [
		"nothing",
		"nothing",
		"nothing",
		"nothing",
		"nothing",
		"nothing",
		"nothing",
		"nothing",
		"nothing",
		"nothing",
		"op.time.dawn",
		"op.time.noon",
		"op.time.sunset",
		"op.time.night",
		"foe.warrior",
		"foe.undead",
		"foe.growth",
		"foe.splinter",
		"foe.wrake",
		"foe.cross"
	    ],
	    "draws": 1,
	    "resetonexhaustion": true
	},
	"alt": [
	    {
		"id": "uncover.enemy",
		"additional": true,
		"chance": 40
	    }
	],
	"linked": [
	    {
		"id": "recon.wasteland.findfarm",
		"chance": 40
	    }
	]
    },
    {
	"id": "recon.wasteland.a.contemnant",
	"actionid": "recon",
	"label": "搜索战火摧残的地区？",
	"startdescription": "走入夜晚那灰暗的死寂，你就能找到什么。也有什么将找上你。",
	"description": "找到了。",
	"requirements": {
	    "friend": -1,
	    "wasteland.a.contemnant": 1
	},
	"warmup": 30,
	"craftable": true,
	"internaldeck": {
	    "spec": [
		"nothing",
		"nothing",
		"nothing",
		"nothing",
		"nothing",
		"nothing",
		"nothing",
		"nothing",
		"nothing",
		"nothing",
		"op.time.dawn",
		"op.time.noon",
		"op.time.sunset",
		"op.time.night",
		"foe.warrior",
		"foe.undead",
		"foe.growth",
		"foe.splinter",
		"foe.wrake",
		"foe.cross"
	    ],
	    "draws": 1,
	    "resetonexhaustion": true
	},
	"alt": [
	    {
		"id": "uncover.enemy",
		"additional": true,
		"chance": 40
	    }
	],
	"linked": [
	    {
		"id": "recon.wasteland.findfarm",
		"chance": 40
	    }
	]
    },
    {
	"id": "recon.wasteland.b.contemnant.scouts",
	"actionid": "recon",
	"label": "搜索战火摧残的地区？",
	"startdescription": "走入夜晚那灰暗的死寂，你就能找到什么。也有什么将找上你。",
	"description": "找到了。",
	"requirements": {
	    "friend": 1,
	    "wasteland.b.contemnant": 1
	},
	"aspects": {
	    "fatiguing": 1
	},
	"warmup": 15,
	"craftable": true,
	"internaldeck": {
	    "spec": [
		"nothing",
		"nothing",
		"nothing",
		"nothing",
		"nothing",
		"nothing",
		"nothing",
		"nothing",
		"nothing",
		"nothing",
		"op.time.dawn",
		"op.time.noon",
		"op.time.sunset",
		"op.time.night",
		"foe.warrior",
		"foe.undead",
		"foe.growth",
		"foe.splinter",
		"foe.wrake"
	    ],
	    "draws": 1,
	    "resetonexhaustion": true
	},
	"alt": [
	    {
		"id": "uncover.enemy",
		"additional": true,
		"chance": 40
	    }
	],
	"linked": [
	    {
		"id": "recon.wasteland.findfarm",
		"chance": 40
	    }
	]
    },
    {
	"id": "recon.wasteland.b.contemnant",
	"actionid": "recon",
	"label": "搜索战火摧残的地区？",
	"startdescription": "走入夜晚那灰暗的死寂，你就能找到什么。也有什么将找上你。",
	"description": "找到了。",
	"requirements": {
	    "friend": -1,
	    "wasteland.b.contemnant": 1
	},
	"warmup": 30,
	"craftable": true,
	"internaldeck": {
	    "spec": [
		"nothing",
		"nothing",
		"nothing",
		"nothing",
		"nothing",
		"nothing",
		"nothing",
		"nothing",
		"nothing",
		"nothing",
		"op.time.dawn",
		"op.time.noon",
		"op.time.sunset",
		"op.time.night",
		"foe.warrior",
		"foe.undead",
		"foe.growth",
		"foe.splinter",
		"foe.wrake"
	    ],
	    "draws": 1,
	    "resetonexhaustion": true
	},
	"alt": [
	    {
		"id": "uncover.enemy",
		"additional": true,
		"chance": 40
	    }
	],
	"linked": [
	    {
		"id": "recon.wasteland.findfarm",
		"chance": 40
	    }
	]
    },
    {
	"id": "recon.wasteland.findfarm",
	"label": "搜索战火摧残的地区？",
	"startdescription": "找到了。",
	"extantreqs": {
	    "foundfarm": -1
	},
	"mutations": [
	    {
		"filter": "wasteland",
		"mutate": "foundfarm",
		"level": 1
	    }
	],
	"effects": {
	    "op.farm.contemnant": 1
	}
    },
    {
	"id": "recon.kaunas.scouts",
	"actionid": "recon",
	"label": "在考纳斯侦察",
	"startdescription": "测量战场。何处可寻得机会？何处存有敌人？",
	"description": "我们找到了一些东西。",
	"requirements": {
	    "friend": 1,
	    "kaunas.here": 1
	},
	"aspects": {
	    "fatiguing": 1
	},
	"warmup": 15,
	"craftable": true,
	"internaldeck": {
	    "spec": [
		"op.ruins",
		"op.ruins",
		"op.sewers",
		"op.time.noon",
		"op.time.night",
		"op.wolves",
		"op.church.contemnant",
		"op.madrugad",
		"side.adeptwinter",
		"side.weaponscache"
	    ],
	    "draws": 1,
	    "resetonexhaustion": true
	},
	"alt": [
	    {
		"id": "uncover.enemy",
		"additional": true,
		"chance": 40
	    },
	    {
		"id": "find.sergei.comeforsword",
		"chance": 30
	    }
	]
    },
    {
	"id": "recon.kaunas",
	"actionid": "recon",
	"label": "在考纳斯侦察",
	"startdescription": "测量战场。何处可寻得机会？何处存有敌人？",
	"description": "我们找到了一些东西。",
	"requirements": {
	    "friend": -1,
	    "kaunas.here": 1
	},
	"warmup": 30,
	"craftable": true,
	"internaldeck": {
	    "spec": [
		"op.ruins",
		"op.ruins",
		"op.sewers",
		"op.time.noon",
		"op.time.night",
		"op.wolves",
		"op.church.contemnant",
		"op.madrugad",
		"side.adeptwinter",
		"side.weaponscache"
	    ],
	    "draws": 1,
	    "resetonexhaustion": true
	},
	"alt": [
	    {
		"id": "uncover.enemy",
		"additional": true,
		"chance": 40
	    },
	    {
		"id": "find.sergei.comeforsword",
		"chance": 30
	    }
	]
    },
    {
	"id": "recon.brest.scouts",
	"actionid": "recon",
	"label": "在布列斯特侦察",
	"startdescription": "测量战场。何处可寻得机会？何处存有敌人？",
	"description": "我们找到了一些东西。",
	"requirements": {
	    "friend": 1,
	    "brest.here": 1
	},
	"aspects": {
	    "fatiguing": 1
	},
	"warmup": 15,
	"craftable": true,
	"internaldeck": {
	    "spec": [
		"op.ruins",
		"op.ruins",
		"op.highplace",
		"op.sewers",
		"op.time.sunset",
		"op.time.night",
		"op.dove",
		"op.cat",
		"op.wolves",
		"op.church.contemnant",
		"side.weaponscache",
		"side.rescuerefugees"
	    ],
	    "draws": 1,
	    "resetonexhaustion": true
	},
	"alt": [
	    {
		"id": "uncover.enemy",
		"additional": true,
		"chance": 40
	    },
	    {
		"id": "find.sergei.comeforsword",
		"chance": 30
	    }
	]
    },
    {
	"id": "recon.brest",
	"actionid": "recon",
	"label": "在布列斯特侦察",
	"startdescription": "测量战场。何处可寻得机会？何处存有敌人？",
	"description": "我们找到了一些东西。",
	"requirements": {
	    "friend": -1,
	    "brest.here": 1
	},
	"warmup": 30,
	"craftable": true,
	"internaldeck": {
	    "spec": [
		"op.ruins",
		"op.ruins",
		"op.highplace",
		"op.sewers",
		"op.time.sunset",
		"op.time.night",
		"op.dove",
		"op.cat",
		"op.wolves",
		"op.church.contemnant",
		"side.weaponscache",
		"side.rescuerefugees"
	    ],
	    "draws": 1,
	    "resetonexhaustion": true
	},
	"alt": [
	    {
		"id": "uncover.enemy",
		"additional": true,
		"chance": 40
	    },
	    {
		"id": "find.sergei.comeforsword",
		"chance": 30
	    }
	]
    },
    {
	"id": "recon.konigsberg.scouts",
	"actionid": "recon",
	"label": "在柯尼斯堡侦察",
	"startdescription": "测量战场。何处可寻得机会？何处存有敌人？",
	"description": "我们找到了一些东西。",
	"requirements": {
	    "friend": 1,
	    "konigsberg.here": 1
	},
	"aspects": {
	    "fatiguing": 1
	},
	"warmup": 15,
	"craftable": true,
	"internaldeck": {
	    "spec": [
		"op.ruins",
		"op.highplace",
		"op.highplace",
		"op.woods",
		"op.time.dawn",
		"op.time.night",
		"op.cat",
		"op.wolves",
		"op.beachcomber",
		"op.farm.contemnant",
		"side.adeptlantern",
		"side.adeptgrail",
		"side.konigsberg"
	    ],
	    "draws": 1,
	    "resetonexhaustion": true
	},
	"alt": [
	    {
		"id": "uncover.enemy",
		"additional": true,
		"chance": 40
	    }
	],
	"linked": [
	    {
		"id": "find.sergei.first",
		"chance": 25
	    },
	    {
		"id": "find.sergei.comeforsword",
		"chance": 30
	    }
	]
    },
    {
	"id": "recon.konigsberg",
	"actionid": "recon",
	"label": "在柯尼斯堡侦察",
	"startdescription": "测量战场。何处可寻得机会？何处存有敌人？",
	"description": "我们找到了一些东西。",
	"requirements": {
	    "friend": -1,
	    "konigsberg.here": 1
	},
	"warmup": 30,
	"craftable": true,
	"internaldeck": {
	    "spec": [
		"op.ruins",
		"op.highplace",
		"op.highplace",
		"op.woods",
		"op.time.dawn",
		"op.time.night",
		"op.cat",
		"op.wolves",
		"op.beachcomber",
		"op.farm.contemnant",
		"side.adeptlantern",
		"side.adeptgrail",
		"side.konigsberg"
	    ],
	    "draws": 1,
	    "resetonexhaustion": true
	},
	"alt": [
	    {
		"id": "uncover.enemy",
		"additional": true,
		"chance": 40
	    }
	],
	"linked": [
	    {
		"id": "find.sergei.first",
		"chance": 25
	    },
	    {
		"id": "find.sergei.comeforsword",
		"chance": 30
	    }
	]
    },
    {
	"id": "recon.gdansk.scouts",
	"actionid": "recon",
	"label": "在格但斯克侦察",
	"startdescription": "测量战场。何处可寻得机会？何处存有敌人？",
	"description": "我们找到了一些东西。",
	"requirements": {
	    "friend": 1,
	    "gdansk.here": 1
	},
	"aspects": {
	    "fatiguing": 1
	},
	"warmup": 15,
	"craftable": true,
	"internaldeck": {
	    "spec": [
		"op.ruins",
		"op.ruins",
		"op.sewers",
		"op.time.sunset",
		"op.time.night",
		"op.time.noon",
		"op.dove",
		"op.church.contemnant",
		"side.adeptgrail",
		"side.weaponscache",
		"op.wolves"
	    ],
	    "draws": 1,
	    "resetonexhaustion": true
	},
	"alt": [
	    {
		"id": "uncover.enemy",
		"additional": true,
		"chance": 40
	    }
	],
	"linked": [
	    {
		"id": "find.sergei.first",
		"chance": 25
	    },
	    {
		"id": "find.sergei.comeforsword",
		"chance": 30
	    }
	]
    },
    {
	"id": "recon.gdansk",
	"actionid": "recon",
	"label": "在格但斯克侦察",
	"startdescription": "测量战场。何处可寻得机会？何处存有敌人？",
	"description": "我们找到了一些东西。",
	"requirements": {
	    "friend": -1,
	    "gdansk.here": 1
	},
	"warmup": 30,
	"craftable": true,
	"internaldeck": {
	    "spec": [
		"op.ruins",
		"op.ruins",
		"op.sewers",
		"op.time.sunset",
		"op.time.night",
		"op.time.noon",
		"op.dove",
		"op.church.contemnant",
		"side.adeptgrail",
		"side.weaponscache",
		"op.wolves"
	    ],
	    "draws": 1,
	    "resetonexhaustion": true
	},
	"alt": [
	    {
		"id": "uncover.enemy",
		"additional": true,
		"chance": 40
	    }
	],
	"linked": [
	    {
		"id": "find.sergei.first",
		"chance": 25
	    },
	    {
		"id": "find.sergei.comeforsword",
		"chance": 30
	    }
	]
    },
    {
	"id": "recon.grudziadz.scouts",
	"actionid": "recon",
	"label": "在格鲁琼兹侦察",
	"startdescription": "测量战场。何处可寻得机会？何处存有敌人？",
	"description": "我们找到了一些东西。",
	"requirements": {
	    "friend": 1,
	    "grudziadz.here": 1
	},
	"aspects": {
	    "fatiguing": 1
	},
	"warmup": 15,
	"craftable": true,
	"internaldeck": {
	    "spec": [
		"op.woods",
		"op.woods",
		"op.sewers",
		"op.ruins",
		"op.time.dawn",
		"op.time.noon",
		"op.cat",
		"op.farm.contemnant",
		"op.velvet",
		"side.rescuerefugees",
		"side.adeptlantern"
	    ],
	    "draws": 1,
	    "resetonexhaustion": true
	},
	"alt": [
	    {
		"id": "uncover.enemy",
		"additional": true,
		"chance": 40
	    }
	],
	"linked": [
	    {
		"id": "find.sergei.first",
		"chance": 25
	    },
	    {
		"id": "find.sergei.comeforsword",
		"chance": 30
	    }
	]
    },
    {
	"id": "recon.grudziadz",
	"actionid": "recon",
	"label": "在格鲁琼兹侦察",
	"startdescription": "测量战场。何处可寻得机会？何处存有敌人？",
	"description": "我们找到了一些东西。",
	"requirements": {
	    "friend": -1,
	    "grudziadz.here": 1
	},
	"warmup": 30,
	"craftable": true,
	"internaldeck": {
	    "spec": [
		"op.woods",
		"op.woods",
		"op.sewers",
		"op.ruins",
		"op.time.dawn",
		"op.time.noon",
		"op.cat",
		"op.farm.contemnant",
		"op.velvet",
		"side.rescuerefugees",
		"side.adeptlantern"
	    ],
	    "draws": 1,
	    "resetonexhaustion": true
	},
	"alt": [
	    {
		"id": "uncover.enemy",
		"additional": true,
		"chance": 40
	    }
	],
	"linked": [
	    {
		"id": "find.sergei.first",
		"chance": 25
	    },
	    {
		"id": "find.sergei.comeforsword",
		"chance": 30
	    }
	]
    },
    {
	"id": "recon.lodz.scouts",
	"actionid": "recon",
	"label": "在罗兹侦察",
	"startdescription": "测量战场。何处可寻得机会？何处存有敌人？",
	"description": "我们找到了一些东西。",
	"requirements": {
	    "friend": 1,
	    "lodz.here": 1
	},
	"aspects": {
	    "fatiguing": 1
	},
	"warmup": 15,
	"craftable": true,
	"internaldeck": {
	    "spec": [
		"op.highplace",
		"op.sewers",
		"op.sewers",
		"op.time.dawn",
		"op.time.sunset",
		"op.cat",
		"op.church.contemnant",
		"op.church.contemnant",
		"side.adeptwinter",
		"side.adeptgrail"
	    ],
	    "draws": 1,
	    "resetonexhaustion": true
	},
	"alt": [
	    {
		"id": "uncover.enemy",
		"additional": true,
		"chance": 40
	    }
	],
	"linked": [
	    {
		"id": "find.sergei.first",
		"chance": 25
	    },
	    {
		"id": "find.sergei.comeforsword",
		"chance": 30
	    }
	]
    },
    {
	"id": "recon.lodz",
	"actionid": "recon",
	"label": "在罗兹侦察",
	"startdescription": "测量战场。何处可寻得机会？何处存有敌人？",
	"description": "我们找到了一些东西。",
	"requirements": {
	    "friend": -1,
	    "lodz.here": 1
	},
	"warmup": 30,
	"craftable": true,
	"internaldeck": {
	    "spec": [
		"op.highplace",
		"op.sewers",
		"op.sewers",
		"op.time.dawn",
		"op.time.sunset",
		"op.cat",
		"op.church.contemnant",
		"op.church.contemnant",
		"side.adeptwinter",
		"side.adeptgrail"
	    ],
	    "draws": 1,
	    "resetonexhaustion": true
	},
	"alt": [
	    {
		"id": "uncover.enemy",
		"additional": true,
		"chance": 40
	    }
	],
	"linked": [
	    {
		"id": "find.sergei.first",
		"chance": 25
	    },
	    {
		"id": "find.sergei.comeforsword",
		"chance": 30
	    }
	]
    },
    {
	"id": "recon.warsaw.scouts",
	"actionid": "recon",
	"label": "在华沙侦察",
	"startdescription": "测量战场。何处可寻得机会？何处存有敌人？",
	"description": "我们找到了一些东西。",
	"requirements": {
	    "friend": 1,
	    "warsaw.here": 1
	},
	"aspects": {
	    "fatiguing": 1
	},
	"warmup": 15,
	"craftable": true,
	"internaldeck": {
	    "spec": [
		"op.ruins",
		"op.ruins",
		"op.sewers",
		"op.sewers",
		"op.time.night",
		"op.time.sunset",
		"op.wolves",
		"op.dove",
		"op.beachcomber",
		"side.rescuerefugees",
		"side.rescuerefugees",
		"side.warsaw"
	    ],
	    "draws": 1,
	    "resetonexhaustion": true
	},
	"alt": [
	    {
		"id": "uncover.enemy",
		"additional": true,
		"chance": 40
	    }
	],
	"linked": [
	    {
		"id": "find.sergei.first",
		"chance": 25
	    },
	    {
		"id": "find.sergei.comeforsword",
		"chance": 30
	    }
	]
    },
    {
	"id": "recon.warsaw",
	"actionid": "recon",
	"label": "在华沙侦察",
	"startdescription": "测量战场。何处可寻得机会？何处存有敌人？",
	"description": "我们找到了一些东西。",
	"requirements": {
	    "friend": -1,
	    "warsaw.here": 1
	},
	"warmup": 30,
	"craftable": true,
	"internaldeck": {
	    "spec": [
		"op.ruins",
		"op.ruins",
		"op.sewers",
		"op.sewers",
		"op.time.night",
		"op.time.sunset",
		"op.wolves",
		"op.dove",
		"op.beachcomber",
		"side.rescuerefugees",
		"side.rescuerefugees",
		"side.warsaw"
	    ],
	    "draws": 1,
	    "resetonexhaustion": true
	},
	"alt": [
	    {
		"id": "uncover.enemy",
		"additional": true,
		"chance": 40
	    }
	],
	"linked": [
	    {
		"id": "find.sergei.first",
		"chance": 25
	    },
	    {
		"id": "find.sergei.comeforsword",
		"chance": 30
	    }
	]
    },
    {
	"id": "recon.lublin.scouts",
	"actionid": "recon",
	"label": "在卢布林侦察",
	"startdescription": "测量战场。何处可寻得机会？何处存有敌人？",
	"description": "我们找到了一些东西。",
	"requirements": {
	    "friend": 1,
	    "lublin.here": 1
	},
	"aspects": {
	    "fatiguing": 1
	},
	"warmup": 15,
	"craftable": true,
	"internaldeck": {
	    "spec": [
		"op.ruins",
		"op.highplace",
		"op.highplace",
		"op.time.night",
		"op.time.noon",
		"op.cat",
		"op.dove",
		"op.church.contemnant",
		"op.church.contemnant",
		"side.weaponscache",
		"side.rescuerefugees",
		"op.wolves"
	    ],
	    "draws": 1,
	    "resetonexhaustion": true
	},
	"alt": [
	    {
		"id": "uncover.enemy",
		"additional": true,
		"chance": 40
	    }
	],
	"linked": [
	    {
		"id": "find.sergei.first",
		"chance": 25
	    },
	    {
		"id": "find.sergei.comeforsword",
		"chance": 30
	    }
	]
    },
    {
	"id": "recon.lublin",
	"actionid": "recon",
	"label": "在卢布林侦察",
	"startdescription": "测量战场。何处可寻得机会？何处存有敌人？",
	"description": "我们找到了一些东西。",
	"requirements": {
	    "friend": -1,
	    "lublin.here": 1
	},
	"warmup": 30,
	"craftable": true,
	"internaldeck": {
	    "spec": [
		"op.ruins",
		"op.highplace",
		"op.highplace",
		"op.time.night",
		"op.time.noon",
		"op.cat",
		"op.dove",
		"op.church.contemnant",
		"op.church.contemnant",
		"side.weaponscache",
		"side.rescuerefugees",
		"op.wolves"
	    ],
	    "draws": 1,
	    "resetonexhaustion": true
	},
	"alt": [
	    {
		"id": "uncover.enemy",
		"additional": true,
		"chance": 40
	    }
	],
	"linked": [
	    {
		"id": "find.sergei.first",
		"chance": 25
	    },
	    {
		"id": "find.sergei.comeforsword",
		"chance": 30
	    }
	]
    },
    {
	"id": "recon.katowice.scouts",
	"actionid": "recon",
	"label": "在卡托维兹侦察",
	"startdescription": "测量战场。何处可寻得机会？何处存有敌人？",
	"description": "我们找到了一些东西。",
	"requirements": {
	    "friend": 1,
	    "katowice.here": 1
	},
	"aspects": {
	    "fatiguing": 1
	},
	"warmup": 15,
	"craftable": true,
	"internaldeck": {
	    "spec": [
		"op.highplace",
		"op.highplace",
		"op.sewers",
		"op.woods",
		"op.time.dawn",
		"op.time.sunset",
		"op.wolves",
		"op.farm.contemnant",
		"side.adeptgrail",
		"side.weaponscache"
	    ],
	    "draws": 1,
	    "resetonexhaustion": true
	},
	"alt": [
	    {
		"id": "uncover.enemy",
		"additional": true,
		"chance": 40
	    }
	],
	"linked": [
	    {
		"id": "find.sergei.first",
		"chance": 25
	    },
	    {
		"id": "find.sergei.comeforsword",
		"chance": 30
	    }
	]
    },
    {
	"id": "recon.katowice",
	"actionid": "recon",
	"label": "在卡托维兹侦察",
	"startdescription": "测量战场。何处可寻得机会？何处存有敌人？",
	"description": "我们找到了一些东西。",
	"requirements": {
	    "friend": -1,
	    "katowice.here": 1
	},
	"warmup": 30,
	"craftable": true,
	"internaldeck": {
	    "spec": [
		"op.highplace",
		"op.highplace",
		"op.sewers",
		"op.woods",
		"op.time.dawn",
		"op.time.sunset",
		"op.wolves",
		"op.farm.contemnant",
		"side.adeptgrail",
		"side.weaponscache"
	    ],
	    "draws": 1,
	    "resetonexhaustion": true
	},
	"alt": [
	    {
		"id": "uncover.enemy",
		"additional": true,
		"chance": 40
	    }
	],
	"linked": [
	    {
		"id": "find.sergei.first",
		"chance": 25
	    },
	    {
		"id": "find.sergei.comeforsword",
		"chance": 30
	    }
	]
    },
    {
	"id": "recon.krakow.scouts",
	"actionid": "recon",
	"label": "在克拉科夫侦察",
	"startdescription": "测量战场。何处可寻得机会？何处存有敌人？",
	"description": "我们找到了一些东西。",
	"requirements": {
	    "friend": 1,
	    "krakow.here": 1
	},
	"aspects": {
	    "fatiguing": 1
	},
	"warmup": 15,
	"craftable": true,
	"internaldeck": {
	    "spec": [
		"op.ruins",
		"op.highplace",
		"op.highplace",
		"op.sewers",
		"op.time.noon",
		"op.time.night",
		"op.dove",
		"op.church.contemnant",
		"op.madrugad",
		"side.adeptwinter",
		"side.adeptlantern",
		"sided.krakow"
	    ],
	    "draws": 1,
	    "resetonexhaustion": true
	},
	"alt": [
	    {
		"id": "uncover.enemy",
		"additional": true,
		"chance": 40
	    }
	],
	"linked": [
	    {
		"id": "find.sergei.first",
		"chance": 25
	    },
	    {
		"id": "find.sergei.comeforsword",
		"chance": 30
	    }
	]
    },
    {
	"id": "recon.krakow",
	"actionid": "recon",
	"label": "在克拉科夫侦察",
	"startdescription": "测量战场。何处可寻得机会？何处存有敌人？",
	"description": "我们找到了一些东西。",
	"requirements": {
	    "friend": -1,
	    "krakow.here": 1
	},
	"warmup": 30,
	"craftable": true,
	"internaldeck": {
	    "spec": [
		"op.ruins",
		"op.highplace",
		"op.highplace",
		"op.sewers",
		"op.time.noon",
		"op.time.night",
		"op.dove",
		"op.church.contemnant",
		"op.madrugad",
		"side.adeptwinter",
		"side.adeptlantern",
		"side.krakow"
	    ],
	    "draws": 1,
	    "resetonexhaustion": true
	},
	"alt": [
	    {
		"id": "uncover.enemy",
		"additional": true,
		"chance": 40
	    }
	],
	"linked": [
	    {
		"id": "find.sergei.first",
		"chance": 25
	    },
	    {
		"id": "find.sergei.comeforsword",
		"chance": 30
	    }
	]
    },
    {
	"id": "recon.vienna.scouts",
	"actionid": "recon",
	"label": "在维也纳侦察",
	"startdescription": "测量战场。何处可寻得机会？何处存有敌人？",
	"description": "我们找到了一些东西。",
	"requirements": {
	    "friend": 1,
	    "vienna.here": 1
	},
	"aspects": {
	    "fatiguing": 1
	},
	"warmup": 15,
	"craftable": true,
	"internaldeck": {
	    "spec": [
		"klei",
		"op.ruins",
		"op.ruins",
		"op.sewers",
		"op.highplace",
		"op.time.dawn",
		"op.time.noon",
		"op.time.night",
		"op.church.contemnant",
		"op.dove",
		"side.adeptlantern",
		"side.adeptwinter",
		"side.vienna"
	    ],
	    "draws": 1,
	    "resetonexhaustion": true
	},
	"alt": [
	    {
		"id": "uncover.enemy",
		"additional": true,
		"chance": 40
	    }
	],
	"linked": [
	    {
		"id": "find.sergei.first",
		"chance": 25
	    },
	    {
		"id": "find.sergei.comeforsword",
		"chance": 30
	    }
	]
    },
    {
	"id": "recon.vienna",
	"actionid": "recon",
	"label": "在维也纳侦察",
	"startdescription": "测量战场。何处可寻得机会？何处存有敌人？",
	"description": "我们找到了一些东西。",
	"requirements": {
	    "friend": -1,
	    "vienna.here": 1
	},
	"warmup": 30,
	"craftable": true,
	"internaldeck": {
	    "spec": [
		"klei",
		"op.ruins",
		"op.ruins",
		"op.sewers",
		"op.highplace",
		"op.time.dawn",
		"op.time.noon",
		"op.time.night",
		"op.church.contemnant",
		"op.dove",
		"side.adeptlantern",
		"side.adeptwinter",
		"side.vienna"
	    ],
	    "draws": 1,
	    "resetonexhaustion": true
	},
	"alt": [
	    {
		"id": "uncover.enemy",
		"additional": true,
		"chance": 40
	    }
	],
	"linked": [
	    {
		"id": "find.sergei.first",
		"chance": 25
	    },
	    {
		"id": "find.sergei.comeforsword",
		"chance": 30
	    }
	]
    },
    {
	"id": "recon.brno.scouts",
	"actionid": "recon",
	"label": "在布尔诺侦察",
	"startdescription": "测量战场。何处可寻得机会？何处存有敌人？",
	"description": "我们找到了一些东西。",
	"requirements": {
	    "friend": 1,
	    "brno.here": 1
	},
	"aspects": {
	    "fatiguing": 1
	},
	"warmup": 15,
	"craftable": true,
	"internaldeck": {
	    "spec": [
		"op.ruins",
		"op.sewers",
		"op.sewers",
		"op.woods",
		"op.time.sunset",
		"op.time.noon",
		"op.church.contemnant",
		"op.wolves",
		"side.weaponscache",
		"side.rescuerefugees"
	    ],
	    "draws": 1,
	    "resetonexhaustion": true
	},
	"alt": [
	    {
		"id": "uncover.enemy",
		"additional": true,
		"chance": 40
	    }
	],
	"linked": [
	    {
		"id": "find.sergei.first",
		"chance": 25
	    },
	    {
		"id": "find.sergei.comeforsword",
		"chance": 30
	    }
	]
    },
    {
	"id": "recon.brno",
	"actionid": "recon",
	"label": "在布尔诺侦察",
	"startdescription": "测量战场。何处可寻得机会？何处存有敌人？",
	"description": "我们找到了一些东西。",
	"requirements": {
	    "friend": -1,
	    "brno.here": 1
	},
	"warmup": 30,
	"craftable": true,
	"internaldeck": {
	    "spec": [
		"op.ruins",
		"op.sewers",
		"op.sewers",
		"op.woods",
		"op.time.sunset",
		"op.time.noon",
		"op.church.contemnant",
		"op.wolves",
		"side.weaponscache",
		"side.rescuerefugees"
	    ],
	    "draws": 1,
	    "resetonexhaustion": true
	},
	"alt": [
	    {
		"id": "uncover.enemy",
		"additional": true,
		"chance": 40
	    }
	],
	"linked": [
	    {
		"id": "find.sergei.first",
		"chance": 25
	    },
	    {
		"id": "find.sergei.comeforsword",
		"chance": 30
	    }
	]
    },
    {
	"id": "recon.prague.scouts",
	"actionid": "recon",
	"label": "在布拉格侦察",
	"startdescription": "测量战场。何处可寻得机会？何处存有敌人？",
	"description": "我们找到了一些东西。",
	"requirements": {
	    "friend": 1,
	    "prague.here": 1
	},
	"aspects": {
	    "fatiguing": 1
	},
	"warmup": 15,
	"craftable": true,
	"internaldeck": {
	    "spec": [
		"op.sewers",
		"op.sewers",
		"op.ruins",
		"op.ruins",
		"op.time.noon",
		"op.time.night",
		"op.church.contemnant",
		"op.dove",
		"op.wolves",
		"op.madrugad",
		"side.weaponscache",
		"side.adeptgrail",
		"side.prague"
	    ],
	    "draws": 1,
	    "resetonexhaustion": true
	},
	"alt": [
	    {
		"id": "uncover.enemy",
		"additional": true,
		"chance": 40
	    }
	],
	"linked": [
	    {
		"id": "find.sergei.first",
		"chance": 25
	    },
	    {
		"id": "find.sergei.comeforsword",
		"chance": 30
	    }
	]
    },
    {
	"id": "recon.prague",
	"actionid": "recon",
	"label": "在布拉格侦察",
	"startdescription": "测量战场。何处可寻得机会？何处存有敌人？",
	"description": "我们找到了一些东西。",
	"requirements": {
	    "friend": -1,
	    "prague.here": 1
	},
	"warmup": 30,
	"craftable": true,
	"internaldeck": {
	    "spec": [
		"op.sewers",
		"op.sewers",
		"op.ruins",
		"op.ruins",
		"op.time.noon",
		"op.time.night",
		"op.church.contemnant",
		"op.dove",
		"op.wolves",
		"op.madrugad",
		"side.weaponscache",
		"side.adeptgrail",
		"side.prague"
	    ],
	    "draws": 1,
	    "resetonexhaustion": true
	},
	"alt": [
	    {
		"id": "uncover.enemy",
		"additional": true,
		"chance": 40
	    }
	],
	"linked": [
	    {
		"id": "find.sergei.first",
		"chance": 25
	    },
	    {
		"id": "find.sergei.comeforsword",
		"chance": 30
	    }
	]
    },
    {
	"id": "recon.liberec.scouts",
	"actionid": "recon",
	"label": "在利贝雷茨侦察",
	"startdescription": "测量战场。何处可寻得机会？何处存有敌人？",
	"description": "我们找到了一些东西。",
	"requirements": {
	    "friend": 1,
	    "liberec.here": 1
	},
	"aspects": {
	    "fatiguing": 1
	},
	"warmup": 15,
	"craftable": true,
	"internaldeck": {
	    "spec": [
		"op.highplace",
		"op.woods",
		"op.woods",
		"op.sewers",
		"op.time.sunset",
		"op.time.night",
		"op.cat",
		"op.dove",
		"op.velvet",
		"side.adeptlantern",
		"side.adeptgrail",
		"side.weaponscache",
		"side.liberec"
	    ],
	    "draws": 1,
	    "resetonexhaustion": true
	},
	"alt": [
	    {
		"id": "uncover.enemy",
		"additional": true,
		"chance": 40
	    }
	],
	"linked": [
	    {
		"id": "find.sergei.first",
		"chance": 25
	    },
	    {
		"id": "find.sergei.comeforsword",
		"chance": 30
	    }
	]
    },
    {
	"id": "recon.liberec",
	"actionid": "recon",
	"label": "在利贝雷茨侦察",
	"startdescription": "测量战场。何处可寻得机会？何处存有敌人？",
	"description": "我们找到了一些东西。",
	"requirements": {
	    "friend": -1,
	    "liberec.here": 1
	},
	"warmup": 30,
	"craftable": true,
	"internaldeck": {
	    "spec": [
		"op.highplace",
		"op.woods",
		"op.woods",
		"op.sewers",
		"op.time.sunset",
		"op.time.night",
		"op.cat",
		"op.dove",
		"op.velvet",
		"side.adeptlantern",
		"side.adeptgrail",
		"side.weaponscache",
		"side.liberec"
	    ],
	    "draws": 1,
	    "resetonexhaustion": true
	},
	"alt": [
	    {
		"id": "uncover.enemy",
		"additional": true,
		"chance": 40
	    }
	],
	"linked": [
	    {
		"id": "find.sergei.first",
		"chance": 25
	    },
	    {
		"id": "find.sergei.comeforsword",
		"chance": 30
	    }
	]
    },
    {
	"id": "recon.dresden.scouts",
	"actionid": "recon",
	"label": "在德累斯顿侦察",
	"startdescription": "测量战场。何处可寻得机会？何处存有敌人？",
	"description": "我们找到了一些东西。",
	"requirements": {
	    "friend": 1,
	    "dresden.here": 1
	},
	"aspects": {
	    "fatiguing": 1
	},
	"warmup": 15,
	"craftable": true,
	"internaldeck": {
	    "spec": [
		"op.ruins",
		"op.ruins",
		"op.sewers",
		"op.time.dawn",
		"op.time.noon",
		"op.wolves",
		"op.beachcomber",
		"side.adeptwinter",
		"side.rescuerefugees",
		"side.dresden"
	    ],
	    "draws": 1,
	    "resetonexhaustion": true
	},
	"alt": [
	    {
		"id": "uncover.enemy",
		"additional": true,
		"chance": 40
	    }
	],
	"linked": [
	    {
		"id": "find.sergei.first",
		"chance": 25
	    },
	    {
		"id": "find.sergei.comeforsword",
		"chance": 30
	    }
	]
    },
    {
	"id": "recon.dresden",
	"actionid": "recon",
	"label": "在德累斯顿侦察",
	"startdescription": "测量战场。何处可寻得机会？何处存有敌人？",
	"description": "我们找到了一些东西。",
	"requirements": {
	    "friend": -1,
	    "dresden.here": 1
	},
	"warmup": 30,
	"craftable": true,
	"internaldeck": {
	    "spec": [
		"op.ruins",
		"op.ruins",
		"op.sewers",
		"op.time.dawn",
		"op.time.noon",
		"op.wolves",
		"op.beachcomber",
		"side.adeptwinter",
		"side.rescuerefugees",
		"side.dresden"
	    ],
	    "draws": 1,
	    "resetonexhaustion": true
	},
	"alt": [
	    {
		"id": "uncover.enemy",
		"additional": true,
		"chance": 40
	    }
	],
	"linked": [
	    {
		"id": "find.sergei.first",
		"chance": 25
	    },
	    {
		"id": "find.sergei.comeforsword",
		"chance": 30
	    }
	]
    },
    {
	"id": "recon.wroclaw.scouts",
	"actionid": "recon",
	"label": "在弗罗茨瓦夫侦察",
	"startdescription": "测量战场。何处可寻得机会？何处存有敌人？",
	"description": "我们找到了一些东西。",
	"requirements": {
	    "friend": 1,
	    "wroclaw.here": 1
	},
	"aspects": {
	    "fatiguing": 1
	},
	"warmup": 15,
	"craftable": true,
	"internaldeck": {
	    "spec": [
		"op.woods",
		"op.ruins",
		"op.sewers",
		"op.highplace",
		"op.time.sunset",
		"op.time.dawn",
		"op.cat",
		"op.madrugad",
		"op.farm.contemnant",
		"side.weaponscache",
		"side.rescuerefugees"
	    ],
	    "draws": 1,
	    "resetonexhaustion": true
	},
	"alt": [
	    {
		"id": "uncover.enemy",
		"additional": true,
		"chance": 40
	    }
	],
	"linked": [
	    {
		"id": "find.sergei.first",
		"chance": 25
	    },
	    {
		"id": "find.sergei.comeforsword",
		"chance": 30
	    }
	]
    },
    {
	"id": "recon.wroclaw",
	"actionid": "recon",
	"label": "在弗罗茨瓦夫侦察",
	"startdescription": "测量战场。何处可寻得机会？何处存有敌人？",
	"description": "我们找到了一些东西。",
	"requirements": {
	    "friend": -1,
	    "wroclaw.here": 1
	},
	"warmup": 30,
	"craftable": true,
	"internaldeck": {
	    "spec": [
		"op.woods",
		"op.ruins",
		"op.sewers",
		"op.highplace",
		"op.time.sunset",
		"op.time.dawn",
		"op.cat",
		"op.madrugad",
		"op.farm.contemnant",
		"side.weaponscache",
		"side.rescuerefugees"
	    ],
	    "draws": 1,
	    "resetonexhaustion": true
	},
	"alt": [
	    {
		"id": "uncover.enemy",
		"additional": true,
		"chance": 40
	    }
	],
	"linked": [
	    {
		"id": "find.sergei.first",
		"chance": 25
	    },
	    {
		"id": "find.sergei.comeforsword",
		"chance": 30
	    }
	]
    },
    {
	"id": "recon.poznan.scouts",
	"actionid": "recon",
	"label": "在波兹南侦察",
	"startdescription": "测量战场。何处可寻得机会？何处存有敌人？",
	"description": "我们找到了一些东西。",
	"requirements": {
	    "friend": 1,
	    "poznan.here": 1
	},
	"aspects": {
	    "fatiguing": 1
	},
	"warmup": 15,
	"craftable": true,
	"internaldeck": {
	    "spec": [
		"op.woods",
		"op.woods",
		"op.ruins",
		"op.time.noon",
		"op.time.night",
		"op.wolves",
		"op.velvet",
		"op.farm.contemnant",
		"side.adeptwinter",
		"side.rescuerefugees"
	    ],
	    "draws": 1,
	    "resetonexhaustion": true
	},
	"alt": [
	    {
		"id": "uncover.enemy",
		"additional": true,
		"chance": 40
	    }
	],
	"linked": [
	    {
		"id": "find.sergei.first",
		"chance": 25
	    },
	    {
		"id": "find.sergei.comeforsword",
		"chance": 30
	    }
	]
    },
    {
	"id": "recon.poznan",
	"actionid": "recon",
	"label": "在波兹南侦察",
	"startdescription": "测量战场。何处可寻得机会？何处存有敌人？",
	"description": "我们找到了一些东西。",
	"requirements": {
	    "friend": -1,
	    "poznan.here": 1
	},
	"warmup": 30,
	"craftable": true,
	"internaldeck": {
	    "spec": [
		"op.woods",
		"op.woods",
		"op.ruins",
		"op.time.noon",
		"op.time.night",
		"op.wolves",
		"op.velvet",
		"op.farm.contemnant",
		"side.adeptwinter",
		"side.rescuerefugees"
	    ],
	    "draws": 1,
	    "resetonexhaustion": true
	},
	"alt": [
	    {
		"id": "uncover.enemy",
		"additional": true,
		"chance": 40
	    }
	],
	"linked": [
	    {
		"id": "find.sergei.first",
		"chance": 25
	    },
	    {
		"id": "find.sergei.comeforsword",
		"chance": 30
	    }
	]
    },
    {
	"id": "recon.szczecin.scouts",
	"actionid": "recon",
	"label": "在什切青侦察",
	"startdescription": "测量战场。何处可寻得机会？何处存有敌人？",
	"description": "我们找到了一些东西。",
	"requirements": {
	    "friend": 1,
	    "szczecin.here": 1
	},
	"aspects": {
	    "fatiguing": 1
	},
	"warmup": 15,
	"craftable": true,
	"internaldeck": {
	    "spec": [
		"op.ruins",
		"op.ruins",
		"op.sewers",
		"op.highplace",
		"op.time.noon",
		"op.time.sunset",
		"op.cat",
		"op.madrugad",
		"op.church.contemnant",
		"side.adeptgrail",
		"side.weaponscache",
		"op.wolves"
	    ],
	    "draws": 1,
	    "resetonexhaustion": true
	},
	"alt": [
	    {
		"id": "uncover.enemy",
		"additional": true,
		"chance": 40
	    }
	],
	"linked": [
	    {
		"id": "find.sergei.first",
		"chance": 25
	    },
	    {
		"id": "find.sergei.comeforsword",
		"chance": 30
	    }
	]
    },
    {
	"id": "recon.szczecin",
	"actionid": "recon",
	"label": "在什切青侦察",
	"startdescription": "测量战场。何处可寻得机会？何处存有敌人？",
	"description": "我们找到了一些东西。",
	"requirements": {
	    "friend": -1,
	    "szczecin.here": 1
	},
	"warmup": 30,
	"craftable": true,
	"internaldeck": {
	    "spec": [
		"op.ruins",
		"op.ruins",
		"op.sewers",
		"op.highplace",
		"op.time.noon",
		"op.time.sunset",
		"op.cat",
		"op.madrugad",
		"op.church.contemnant",
		"side.adeptgrail",
		"side.weaponscache",
		"op.wolves"
	    ],
	    "draws": 1,
	    "resetonexhaustion": true
	},
	"alt": [
	    {
		"id": "uncover.enemy",
		"additional": true,
		"chance": 40
	    }
	],
	"linked": [
	    {
		"id": "find.sergei.first",
		"chance": 25
	    },
	    {
		"id": "find.sergei.comeforsword",
		"chance": 30
	    }
	]
    },
    {
	"id": "recon.berlin.scouts",
	"actionid": "recon",
	"label": "在柏林侦察",
	"startdescription": "测量战场。何处可寻得机会？何处存有敌人？",
	"description": "我们找到了一些东西。",
	"requirements": {
	    "friend": 1,
	    "berlin.here": 1
	},
	"aspects": {
	    "fatiguing": 1
	},
	"warmup": 15,
	"craftable": true,
	"internaldeck": {
	    "spec": [
		"op.ruins",
		"op.ruins",
		"op.highplace",
		"op.highplace",
		"op.sewers",
		"op.time.noon",
		"op.time.sunset",
		"op.time.night",
		"op.thelionsmith",
		"op.thecolonel",
		"op.wolfdivided"
	    ],
	    "draws": 1,
	    "resetonexhaustion": true
	},
	"alt": [
	    {
		"id": "uncover.enemy",
		"additional": true,
		"chance": 40
	    }
	],
	"linked": [
	    {
		"id": "find.sergei.first",
		"chance": 25
	    },
	    {
		"id": "find.sergei.comeforsword",
		"chance": 30
	    }
	]
    },
    {
	"id": "recon.berlin",
	"actionid": "recon",
	"label": "在柏林侦察",
	"startdescription": "测量战场。何处可寻得机会？何处存有敌人？",
	"description": "我们找到了一些东西。",
	"requirements": {
	    "friend": -1,
	    "berlin.here": 1
	},
	"warmup": 30,
	"craftable": true,
	"internaldeck": {
	    "spec": [
		"op.ruins",
		"op.ruins",
		"op.highplace",
		"op.highplace",
		"op.sewers",
		"op.time.noon",
		"op.time.sunset",
		"op.time.night",
		"op.thelionsmith",
		"op.thecolonel",
		"op.wolfdivided"
	    ],
	    "draws": 1,
	    "resetonexhaustion": true
	},
	"alt": [
	    {
		"id": "uncover.enemy",
		"additional": true,
		"chance": 40
	    }
	],
	"linked": [
	    {
		"id": "find.sergei.first",
		"chance": 25
	    },
	    {
		"id": "find.sergei.comeforsword",
		"chance": 30
	    }
	]
    },
]
}